{"ampData":{"Chip#1":["103 105 106 105 102 103 101 97 107 104 101 103 0","111 101 110 111 112 112 110 104 110 105 111 108 1","104 99 105 105 106 101 102 96 100 94 100 98 2","108 102 110 109 111 108 103 102 104 103 104 103 3","100 100 103 105 105 101 92 96 97 94 96 99 4","106 104 110 109 106 104 104 102 103 101 104 99 5","105 99 106 107 103 104 99 96 101 100 99 99 6","104 101 108 102 102 100 99 96 100 100 100 101 7","115 105 111 109 111 107 105 106 103 104 104 103 8","105 100 108 106 106 104 99 100 101 103 105 99 9","98 97 101 99 100 96 99 94 100 95 99 101 10","102 93 103 101 99 100 96 94 100 96 97 15000 11"],"Chip#2":["80 102 102 97 98 98 97 91 56 99 96 100 0","80 100 104 95 98 96 97 93 89 99 96 108 1","79 99 102 95 101 97 100 90 89 102 98 105 2","81 99 100 97 99 97 94 95 89 100 97 108 3","80 99 97 98 100 94 93 95 89 100 96 104 4","83 102 102 95 103 97 97 93 56 101 98 103 5","84 104 103 98 100 97 100 103 89 102 102 105 6","82 101 97 93 99 100 100 93 89 102 100 103 7","86 102 104 100 103 100 106 103 89 109 104 112 8","80 99 95 97 99 99 96 95 89 100 96 107 9","85 99 100 98 101 99 102 98 89 106 103 109 10","80 101 101 99 96 100 98 97 89 102 97 15000 11"]},"meltData":null,"sampleName":[["1","2","3","4",null,null,null,null],[null,null,null,null,null,null,null,null]],"sampleQuant":[["","","","",null,null,null,null],[null,null,null,null,null,null,null,null]],"sampleType":[["Unknown","Unknown","Unknown","Unknown",null,null,null,null],[null,null,null,null,null,null,null,null]],"sampleTypeIndex":[[0,0,0,0,0,0,0,0],[0,0,0,0,0,0,0,0]],"sampleQuantUnit":[["Copies","Copies","Copies","Copies",null,null,null,null],[null,null,null,null,null,null,null,null]],"sampleQuantUnitIndex":[[0,0,0,0,0,0,0,0],[0,0,0,0,0,0,0,0]],"sampleAssayIndex":[[0,0,0,0,0,0,0,0],[0,0,0,0,0,0,0,0]],"sampleExtractMethodIndex":[[0,0,0,0,0,0,0,0],[0,0,0,0,0,0,0,0]],"assayChanType":[null,null,null,null],"assayChanTypeIndex":[0,0,0,0],"assayChanStdSlope":[null,null,null,null],"assayChanStdIntercept":[null,null,null,null],"gainMode":[0,0,0,0],"curfitStartCycle":3,"curfitMinCt":13,"curfitCtTh":0.08,"emname":"Experiment_01-25-2020_212227","emdatetime":"2020-01-25T21:22:27.4860671-08:00","endatetime":"2020-01-25T21:22:27.4860671-08:00","chanonetype":"FAM","chanonedes":"btg","chantwotype":"HEX","chantwodes":"re","chanthreetype":"ROX","chanthreedes":"","chanfourtype":"Cy5","chanfourdes":"","A1des":"1","A2des":"2","A3des":"3","A4des":"4","A5des":"","A6des":"","A7des":"","A8des":"","B1des":"","B2des":"","B3des":"","B4des":"","B5des":"","B6des":"","B7des":"","B8des":"","programMode":"","ImgFileName":"ImgData\\ADCData_2020-01-25_ 092142.txt","ImgFileName2":null,"SetFileName":null,"CyderNum":0,"DebugModelDataList":[{"Hotlid":105.0,"InitaldenaturationStart":45.0,"Initaldenaturation":95.0,"InitaldenaTime":60.0,"DenaturatingStart":95.0,"Denaturating":95.0,"DenaturatingTime":10.0,"AnnealingStart":95.0,"Annealing":60.0,"AnnealingTime":15.0,"ExtensionStart":60.0,"Extension":72.0,"ExtensionTime":20.0,"HoldonStart":72.0,"Holdon":50.0,"HoldonTime":60.0,"Cycle":40,"stageIndex":3,"Step4Start":0.0,"Step4":0.0,"Step4Time":0.0,"InitaldenaturationStart2":0.0,"Initaldenaturation2":0.0,"InitaldenaTime2":0.0,"MeltStart":50.0,"MeltEnd":73.8,"MeltStartTime":10.0,"MeltEndTime":10.0,"ifpz":0,"StepCount":3,"InitDenatureStepCount":1,"cyclestate":0,"enMelt":true}],"CbooChan1":true,"CbooChan2":true,"CbooChan3":false,"CbooChan4":false,"enAutoInt":false,"dpStr":"","OpName":"","OpNotes":"","DebugLog":null,"crossTalk21":0.08,"crossTalk12":0.09,"crossTalk23":0.055,"crossTalk32":0.02,"crossTalk43":0.0,"crossTalk34":0.02,"confiTh":0.15,"ampEffTh":0.15,"snrTh":0.1}